odoo/addons/account_analytic_default_purchase/README.rst
odoo/addons/account_analytic_default_purchase/__init__.py
odoo/addons/account_analytic_default_purchase/__manifest__.py
odoo/addons/account_analytic_default_purchase/i18n/account_analytic_default_purchase.pot
odoo/addons/account_analytic_default_purchase/i18n/de.po
odoo/addons/account_analytic_default_purchase/i18n/it.po
odoo/addons/account_analytic_default_purchase/i18n/ja_JP.po
odoo/addons/account_analytic_default_purchase/i18n/pt.po
odoo/addons/account_analytic_default_purchase/i18n/pt_BR.po
odoo/addons/account_analytic_default_purchase/i18n/sl.po
odoo/addons/account_analytic_default_purchase/models/__init__.py
odoo/addons/account_analytic_default_purchase/models/purchase.py
odoo/addons/account_analytic_default_purchase/readme/CONTRIBUTORS.rst
odoo/addons/account_analytic_default_purchase/readme/DESCRIPTION.rst
odoo/addons/account_analytic_default_purchase/static/description/icon.png
odoo/addons/account_analytic_default_purchase/static/description/index.html
odoo/addons/account_analytic_default_purchase/tests/__init__.py
odoo/addons/account_analytic_default_purchase/tests/test_purchase_analytic_default_purchase.py
odoo12_addon_account_analytic_default_purchase-12.0.1.0.0.99.dev18.dist-info/METADATA
odoo12_addon_account_analytic_default_purchase-12.0.1.0.0.99.dev18.dist-info/WHEEL
odoo12_addon_account_analytic_default_purchase-12.0.1.0.0.99.dev18.dist-info/top_level.txt
odoo12_addon_account_analytic_default_purchase-12.0.1.0.0.99.dev18.dist-info/RECORD
